ncio/__init__.py
ncio/_version.py
ncio/ncinfo.py
ncio/ncread.py
ncio/netcdfio.py
ncio-1.0.1.dist-info/AUTHORS.rst
ncio-1.0.1.dist-info/LICENSE
ncio-1.0.1.dist-info/METADATA
ncio-1.0.1.dist-info/WHEEL
ncio-1.0.1.dist-info/top_level.txt
ncio-1.0.1.dist-info/RECORD
